chensir_mcp_demo/__init__.py
chensir_mcp_demo-0.1.0.dist-info/WHEEL
chensir_mcp_demo-0.1.0.dist-info/entry_points.txt
chensir_mcp_demo-0.1.0.dist-info/METADATA
chensir_mcp_demo-0.1.0.dist-info/RECORD
