Metadata-Version: 2.3
Name: chensir-mcp-demo
Version: 0.1.0
Summary: Add your description here
Author: chensir
Author-email: chensir <1791933520@qq.com>
Requires-Dist: mcp[cli]>=1.20.0
Requires-Python: >=3.13
